iminuit/__init__.py
iminuit/_core.cp310-win32.pyd
iminuit/_deprecated.py
iminuit/_hide_modules.py
iminuit/_optional_dependencies.py
iminuit/_parse_version.py
iminuit/_repr_html.py
iminuit/_repr_text.py
iminuit/cost.py
iminuit/experimental.py
iminuit/minimize.py
iminuit/minuit.py
iminuit/pdg_format.py
iminuit/testing.py
iminuit/typing.py
iminuit/util.py
iminuit/warnings.py
iminuit-2.29.0.dist-info/METADATA
iminuit-2.29.0.dist-info/WHEEL
iminuit-2.29.0.dist-info/licenses/LICENSE
iminuit-2.29.0.dist-info/RECORD
