Metadata-Version: 2.1
Name: iminuit
Version: 2.29.0
Summary: Jupyter-friendly Python frontend for MINUIT2 in C++
Maintainer-Email: Hans Dembinski <hans.dembinski@gmail.com>
License: Minuit is from SEAL Minuit It's LGPL v2
Classifier: Development Status :: 5 - Production/Stable
Classifier: Intended Audience :: Science/Research
Classifier: Intended Audience :: Developers
Classifier: License :: OSI Approved :: MIT License
Classifier: License :: OSI Approved :: GNU Library or Lesser General Public License (LGPL)
Classifier: Programming Language :: C++
Classifier: Programming Language :: Python
Classifier: Programming Language :: Python :: 3
Classifier: Programming Language :: Python :: 3 :: Only
Classifier: Programming Language :: Python :: Implementation :: CPython
Classifier: Programming Language :: Python :: Implementation :: PyPy
Classifier: Topic :: Software Development
Classifier: Topic :: Scientific/Engineering :: Physics
Classifier: Topic :: Scientific/Engineering :: Mathematics
Classifier: Operating System :: Microsoft :: Windows
Classifier: Operating System :: POSIX
Classifier: Operating System :: Unix
Classifier: Operating System :: MacOS
Project-URL: Repository, http://github.com/scikit-hep/iminuit
Project-URL: Documentation, https://scikit-hep.org/iminuit
Requires-Python: >=3.9
Requires-Dist: numpy>=1.21
Requires-Dist: coverage; extra == "test"
Requires-Dist: ipywidgets; extra == "test"
Requires-Dist: ipykernel; extra == "test"
Requires-Dist: joblib; extra == "test"
Requires-Dist: jacobi; extra == "test"
Requires-Dist: matplotlib; extra == "test"
Requires-Dist: numpy; extra == "test"
Requires-Dist: numba; platform_python_implementation == "CPython" and extra == "test"
Requires-Dist: numba-stats; platform_python_implementation == "CPython" and extra == "test"
Requires-Dist: pytest; extra == "test"
Requires-Dist: pytest-xdist; extra == "test"
Requires-Dist: scipy; extra == "test"
Requires-Dist: tabulate; extra == "test"
Requires-Dist: boost_histogram; extra == "test"
Requires-Dist: resample; extra == "test"
Requires-Dist: unicodeitplus; extra == "test"
Requires-Dist: pydantic; extra == "test"
Requires-Dist: annotated_types; extra == "test"
Requires-Dist: sphinx-rtd-theme; extra == "doc"
Requires-Dist: nbsphinx; extra == "doc"
Requires-Dist: nbconvert; extra == "doc"
Requires-Dist: nbformat; extra == "doc"
Requires-Dist: jupyter_client; extra == "doc"
Requires-Dist: ipykernel; extra == "doc"
Requires-Dist: jax; extra == "doc"
Requires-Dist: jaxlib; extra == "doc"
Requires-Dist: pytest-xdist; extra == "doc"
Provides-Extra: test
Provides-Extra: doc
